README.md
setup.py
src/task_manage/__init__.py
src/task_manage.egg-info/PKG-INFO
src/task_manage.egg-info/SOURCES.txt
src/task_manage.egg-info/dependency_links.txt
src/task_manage.egg-info/entry_points.txt
src/task_manage.egg-info/not-zip-safe
src/task_manage.egg-info/requires.txt
src/task_manage.egg-info/top_level.txt
src/task_manage/client/__init__.py
src/task_manage/client/main.py
src/task_manage/config/__init__.py
src/task_manage/config/config.cfg
src/task_manage/config/config.win.cfg
src/task_manage/config/taskmd.sh
src/task_manage/server/__init__.py
src/task_manage/server/bottle.py
src/task_manage/server/main.py
src/task_manage/server/task.py