Metadata-Version: 2.1
Name: task-manage
Version: 1.0.5.5
Summary: A lightweight timed task execution system, supporting python, nodejs, and all command-line tasks
Home-page: https://github.com/try520/task-manage
Author: tianling
Author-email: 34492114@qq.com
License: MIT Licence
Keywords: cron,task,cmd
Platform: UNKNOWN
Requires-Python: >=3.5
